{
  "id_personal": 1,
  "name": "David Guadamuz Elizondo",
  "title": "Desarrollador Full Stack",
  "email": "jose.guadamuz.elizondo@est.una.ac.cr",
  "location": "Nicoya, Costa Rica",
  "bio": "Desarrollador Full Stack con experiencia en tecnologías modernas como React, Node.js y .NET C#. Estudiante de Ingeniería en Sistemas de Información con enfoque en el desarrollo de soluciones web completas y escalables, con habilidades balanceadas en backend y frontend.",
  "socialLinks": [
    {
      "id_social": 1,
      "platform": "GitHub",
      "url": "https://github.com/DavElizG",
      "icon": "github"
    },
    {
      "id_social": 2,
      "platform": "LinkedIn",
      "url": "https://www.linkedin.com/in/jose-guadamuz-elizondo-8288a5354/",
      "icon": "linkedin"
    }
  ]
}